django_model_inspector/__init__.py
django_model_inspector/inspector.py
django_model_inspector/sdk_settings.py
django_model_inspector/views.py
dmi/__init__.py
dmi/inspector.py
dmi/sdk_settings.py
dmi/views.py
django_model_inspector-1.0.3.dist-info/LICENSE
django_model_inspector-1.0.3.dist-info/METADATA
django_model_inspector-1.0.3.dist-info/WHEEL
django_model_inspector-1.0.3.dist-info/top_level.txt
django_model_inspector-1.0.3.dist-info/RECORD
