Metadata-Version: 2.1
Name: django-model-inspector
Version: 1.0.3
Summary: A utility to inspect Django model schemas
Home-page: https://github.com/mowzlisre/django-model-inspector
Author: Mowzli Sre Mohan Dass
Author-email: speak2mowzli@gmail.com
Classifier: Programming Language :: Python :: 3
Classifier: Framework :: Django
Classifier: License :: OSI Approved :: MIT License
Classifier: Operating System :: OS Independent
Requires-Python: >=3.6
License-File: LICENSE
Requires-Dist: Django>=3.2
